<?xml version="1.0" encoding="UTF-8" standalone="no"?>
<organizationalModel><participantTypeList><participantType code="orgRole" description="机构和角色" displayName="机构和角色" jointParticipantType="true" leafParticipant="false" priority="5" showAtRootArea="false"><juniorParticipantTypeCodes>org</juniorParticipantTypeCodes><juniorParticipantTypeCodes>role</juniorParticipantTypeCodes><jointTypeCodeList><jointTypeCode>org</jointTypeCode><jointTypeCode>role</jointTypeCode></jointTypeCodeList></participantType><participantType code="position" description="岗位" displayName="岗位" jointParticipantType="false" leafParticipant="false" priority="1" showAtRootArea="false"><juniorParticipantTypeCodes>position</juniorParticipantTypeCodes><juniorParticipantTypeCodes>emp</juniorParticipantTypeCodes></participantType><participantType code="role" description="角色" displayName="角色" jointParticipantType="false" leafParticipant="false" priority="2" showAtRootArea="true"><juniorParticipantTypeCodes>emp</juniorParticipantTypeCodes></participantType><participantType code="emp" description="员工" displayName="员工" jointParticipantType="false" leafParticipant="true" priority="1" showAtRootArea="false"/><participantType code="group" description="工作组" displayName="工作组" jointParticipantType="false" leafParticipant="false" priority="4" showAtRootArea="true"><juniorParticipantTypeCodes>group</juniorParticipantTypeCodes><juniorParticipantTypeCodes>position</juniorParticipantTypeCodes><juniorParticipantTypeCodes>emp</juniorParticipantTypeCodes></participantType><participantType code="org" description="机构" displayName="机构" jointParticipantType="false" leafParticipant="false" priority="4" showAtRootArea="true"><juniorParticipantTypeCodes>org</juniorParticipantTypeCodes><juniorParticipantTypeCodes>position</juniorParticipantTypeCodes><juniorParticipantTypeCodes>emp</juniorParticipantTypeCodes></participantType></participantTypeList><participantGroups><participantGroup extended="1" type="role"><participant extended="1" id="-1" index="1" name="流程管理员" type="role"/><participant extended="1" id="-2" index="2" name="流程定制员" type="role"/><participant extended="1" id="-3" index="3" name="流程配置员" type="role"/><participant extended="1" id="-4" index="4" name="目录管理员" type="role"/><participant extended="1" id="-5" index="5" name="统计分析员" type="role"/><participant extended="1" id="1" index="6" name="系统管理员" type="role"/></participantGroup><participantGroup extended="1" type="group"/><participantGroup extended="1" type="org"/></participantGroups></organizationalModel>